create_tomochain_masternode/__init__.py
create_tomochain_masternode/envs.py
create_tomochain_masternode/main.py
create_tomochain_masternode/templates/__init__.py
create_tomochain_masternode/templates/compose.py
create_tomochain_masternode/templates/env.py
create_tomochain_masternode-1.2.6.dist-info/entry_points.txt
create_tomochain_masternode-1.2.6.dist-info/WHEEL
create_tomochain_masternode-1.2.6.dist-info/METADATA
create_tomochain_masternode-1.2.6.dist-info/RECORD
